LICENSE
lol_voice/__init__.py
lol_voice/base.py
lol_voice/formats/__init__.py
lol_voice/formats/BIN.py
lol_voice/formats/BNK.py
lol_voice/formats/section/__init__.py
lol_voice/formats/section/BKHD.py
lol_voice/formats/section/DATA.py
lol_voice/formats/section/DIDX.py
lol_voice/formats/section/HIRC.py
lol_voice/formats/WAD.py
lol_voice/formats/WPK.py
lol_voice/index.py
lol_voice/tools/__init__.py
lol_voice/tools/Binary/__init__.py
lol_voice/tools/Binary/reader.py
requirements.txt
lol_voice-1.0.4.1.dist-info/LICENSE
lol_voice-1.0.4.1.dist-info/METADATA
lol_voice-1.0.4.1.dist-info/WHEEL
lol_voice-1.0.4.1.dist-info/RECORD
