Metadata-Version: 2.1
Name: lol-voice
Version: 1.0.4.1
Summary: 通过解析英雄联盟游戏内WAD、BNK、WPK、BIN等文件来提取音频文件，并可以按照触发事件分类
Home-page: https://github.com/Virace/py-bnk-extract
License: GPL-3.0-only
Keywords: league,wad,bnk
Author: Virace
Author-email: Virace@aliyun.com
Requires-Python: >=3.8
Classifier: Development Status :: 5 - Production/Stable
Classifier: License :: OSI Approved :: GNU General Public License v3 (GPLv3)
Classifier: Operating System :: OS Independent
Classifier: Programming Language :: Python
Classifier: Programming Language :: Python :: 3
Classifier: Programming Language :: Python :: 3.8
Classifier: Programming Language :: Python :: 3.9
Classifier: Programming Language :: Python :: 3.10
Classifier: Programming Language :: Python :: 3.11
Classifier: Programming Language :: Python :: 3.12
Classifier: Programming Language :: Python :: 3 :: Only
Requires-Dist: loguru (>=0.6.0,<0.7.0)
Requires-Dist: xxhash (>=3.0.0,<4.0.0)
Requires-Dist: zstd (>=1.5.2.5,<2.0.0.0)
Project-URL: Bug Tracker, https://github.com/Virace/py-bnk-extract/issues
Project-URL: Repository, https://github.com/Virace/py-bnk-extract
